README.md
setup.py
Balok/__init__.py
Balok/balokruang.py
hitungbalok_30.egg-info/PKG-INFO
hitungbalok_30.egg-info/SOURCES.txt
hitungbalok_30.egg-info/dependency_links.txt
hitungbalok_30.egg-info/top_level.txt