Metadata-Version: 2.1
Name: hitungbalok-30
Version: 0.0.1
Summary: Library Python untuk menghitung keliling balok.
Home-page: https://github.com/rizalfarhan/Hitung-Balok
Author: rizalfarhan
Author-email: <rizalfarhannanda@gmail.com>
License: MIT
Keywords: balok,ruang
Platform: UNKNOWN
Classifier: Development Status :: 1 - Planning
